mosfit/__init__.py
mosfit/__main__.py
mosfit/constants.py
mosfit/contributors.txt
mosfit/converter.py
mosfit/dependencies.txt
mosfit/fetcher.py
mosfit/fitter.py
mosfit/logo.txt
mosfit/main.py
mosfit/model.py
mosfit/mossampler.py
mosfit/plotting.py
mosfit/printer.py
mosfit/requirements.txt
mosfit/strings.json
mosfit/utils.py
mosfit/cache/.gitkeep
mosfit/jupyter/mosfit.ipynb
mosfit/models/model.json
mosfit/models/types.json
mosfit/models/bns/bns.json
mosfit/models/bns/parameters.json
mosfit/models/bns_generative/bns_generative.json
mosfit/models/bns_generative/parameters.json
mosfit/models/bns_magnetar/bns_magnetar.json
mosfit/models/bns_magnetar/parameters.json
mosfit/models/csm/csm.json
mosfit/models/csm/parameters.json
mosfit/models/csm/data/csm_table.dat
mosfit/models/csm/data/info.txt
mosfit/models/csmni/csmni.json
mosfit/models/csmni/parameters.json
mosfit/models/default/default.json
mosfit/models/default/parameters.json
mosfit/models/default/parameters_test.json
mosfit/models/exppow/exppow.json
mosfit/models/exppow/parameters.json
mosfit/models/fallback/fallback.json
mosfit/models/fallback/parameters.json
mosfit/models/ia/ia.json
mosfit/models/ia/parameters.json
mosfit/models/ic/ic.json
mosfit/models/ic/parameters.json
mosfit/models/kilonova/kilonova.json
mosfit/models/kilonova/parameters.json
mosfit/models/magnetar/magnetar.json
mosfit/models/magnetar/parameters.json
mosfit/models/magni/magni.json
mosfit/models/magni/parameters.json
mosfit/models/nsbh/nsbh.json
mosfit/models/nsbh/parameters.json
mosfit/models/nsbh_generative/nsbh_generative.json
mosfit/models/nsbh_generative/parameters.json
mosfit/models/rprocess/parameters.json
mosfit/models/rprocess/rprocess.json
mosfit/models/shockni/parameters.json
mosfit/models/shockni/shockni.json
mosfit/models/slsn/parameters.json
mosfit/models/slsn/slsn.json
mosfit/models/slsnni/parameters.json
mosfit/models/slsnni/slsnni.json
mosfit/models/tde/parameters.json
mosfit/models/tde/tde.json
mosfit/models/tde/data/info.txt
mosfit-1.2.dist-info/LICENSE
mosfit-1.2.dist-info/METADATA
mosfit-1.2.dist-info/WHEEL
mosfit-1.2.dist-info/entry_points.txt
mosfit-1.2.dist-info/top_level.txt
mosfit-1.2.dist-info/RECORD
