Metadata-Version: 2.1
Name: mosfit
Version: 1.2
Summary: Modular software for fitting semi-analytical model predictions to observed astronomical transient data.
Home-page: https://github.com/guillochon/mosfit
Download-URL: https://github.com/guillochon/mosfit/tarball/1.2
Author: & 
Author-email: guillochon@gmail.com
License: MIT
Keywords: astronomy,fitting,monte carlo,modeling
Classifier: Development Status :: 5 - Production/Stable
Classifier: License :: OSI Approved :: MIT License
Classifier: Natural Language :: English
Classifier: Programming Language :: Python :: 2.7
Classifier: Programming Language :: Python :: 3
Classifier: Topic :: Scientific/Engineering :: Astronomy
Classifier: Topic :: Scientific/Engineering :: Physics
License-File: LICENSE
Requires-Dist: astrocats>=0.3.33
Requires-Dist: astropy>=5.0.1
Requires-Dist: Cython>=3.0.0
Requires-Dist: dynesty>=2.0.0
Requires-Dist: emcee>=3.0.2
Requires-Dist: extinction>=0.2.2
Requires-Dist: inflect>=1.0.0
Requires-Dist: matplotlib>=3.0.0
Requires-Dist: mpi4py==3.1.6
Requires-Dist: nbstripout>=0.2.9
Requires-Dist: numexpr>=2.6.1
Requires-Dist: numpy<=1.26.4
Requires-Dist: palettable>=2.1.1
Requires-Dist: schwimmbad==0.3.0
Requires-Dist: scipy>=1.2
Requires-Dist: seaborn>=0.7.1
Requires-Dist: six>=1.0.0
